BcdaQWidgets-2017.3.0.dist-info/DESCRIPTION.rst
BcdaQWidgets-2017.3.0.dist-info/METADATA
BcdaQWidgets-2017.3.0.dist-info/RECORD
BcdaQWidgets-2017.3.0.dist-info/WHEEL
BcdaQWidgets-2017.3.0.dist-info/entry_points.txt
BcdaQWidgets-2017.3.0.dist-info/metadata.json
BcdaQWidgets-2017.3.0.dist-info/top_level.txt
bcdaqwidgets/LICENSE.txt
bcdaqwidgets/__init__.py
bcdaqwidgets/_version.py
bcdaqwidgets/bcdaqwidgets.py
bcdaqwidgets/devel_pvview.py
bcdaqwidgets/pvview.py
bcdaqwidgets/pyqt4_demo.py
bcdaqwidgets_demos/__init__.py
bcdaqwidgets_demos/pyqt4_probe.py
bcdaqwidgets_demos/vlinac.py
motorqt_demo/__init__.py
motorqt_demo/devel_motor_qt.py
motorqt_demo/listpanel.py
motorqt_demo/mainwindow.py
motorqt_demo/motor_qt.py
motorqt_demo/multimotor.py
motorqt_demo/new_motor_qt.py
motorqt_demo/tooltips.py
