Metadata-Version: 2.0
Name: BcdaQWidgets
Version: 2017.3.0
Summary: PyEpics-aware PyQt widgets for the APS.
Home-page: http://bcdaqwidgets.readthedocs.org
Author: Pete Jemian, Cayla Suarez
Author-email: jemian@anl.gov
License: (c) 2009-2017, UChicago Argonne, LLC (see LICENSE file for details)
Platform: UNKNOWN
Classifier: Development Status :: 4 - Beta
Classifier: Environment :: Console
Classifier: Environment :: Web Environment
Classifier: Intended Audience :: Science/Research
Classifier: License :: Free To Use But Restricted
Classifier: Operating System :: OS Independent
Classifier: Programming Language :: Python
Classifier: Topic :: Scientific/Engineering
Classifier: Topic :: Software Development :: Embedded Systems
Classifier: Topic :: Software Development :: Libraries :: Python Modules
Classifier: Topic :: Utilities
Requires-Dist: pyepics
